workflow/__init__.py
workflow/workflow.py
ecmind_blue_client_workflow-0.0.13.dist-info/LICENSE
ecmind_blue_client_workflow-0.0.13.dist-info/METADATA
ecmind_blue_client_workflow-0.0.13.dist-info/WHEEL
ecmind_blue_client_workflow-0.0.13.dist-info/top_level.txt
ecmind_blue_client_workflow-0.0.13.dist-info/RECORD
